{"4\u53f7\u7ebf|Line four||\u4e0a\u884c": 180, "4\u53f7\u7ebf|Line four||\u4e0b\u884c": 100, "2\u53f7\u7ebf|Line two||\u4e0b\u884c": 110, "1\u53f7\u7ebf|Line one||\u4e0b\u884c": 60, "6\u53f7\u7ebf|Line six||\u4e0a\u884c": 40, "2\u53f7\u7ebf|Line two||\u4e0a\u884c": 80, "\u65e5\u5149\u7ebf|\u65e5\u5149\u7dda|Nikko Line||\u5317": 180, "1\u53f7\u7ebf|Line one||\u4e0a\u884c": 60, "\u65e5\u5149\u7ebf|\u65e5\u5149\u7dda|Nikko Line||\u5357": 180, "\u4e91\u5c71\u57ce\u94c1\u8bd5\u8f66\u573a\u6d4b\u8bd5\u8def\u7ebf||\u4e0b\u884c": 50, "\u4e91\u5c71\u57ce\u94c1\u8bd5\u8f66\u573a\u6d4b\u8bd5\u8def\u7ebf||\u4e0a\u884c": 50, "\u4e91\u5c71\u8f7b\u94c1 601\u8def|light rail 601||\u4e0b\u884c": 50, "\u4e91\u5c71\u8f7b\u94c1 601\u8def|light rail 601||\u4e0a\u884c": 50, "6\u53f7\u7ebf|Line six||\u4e0b\u884c": 50, "\u673a\u573a\u5feb\u7ebf|Airport Express||\u4e0b\u884c": 90, "\u660e\u73e0\u7ebf|Pearl Line||\u5317\u884c": 40, "1\u8def||\u4e0b\u884c\u516c\u4ea4": 10}